setup.py
dbscheduler/__init__.py
dbscheduler/app.py
dbscheduler/models.py
dbscheduler/schedulers.py
dbscheduler/utils.py
dbscheduler/migrations/0001_initial.py
dbscheduler/migrations/__init__.py
dbscheduler/tests/__init__.py
dbscheduler/tests/test_scheduler.py
django_celery_dbscheduler.egg-info/PKG-INFO
django_celery_dbscheduler.egg-info/SOURCES.txt
django_celery_dbscheduler.egg-info/dependency_links.txt
django_celery_dbscheduler.egg-info/not-zip-safe
django_celery_dbscheduler.egg-info/requires.txt
django_celery_dbscheduler.egg-info/top_level.txt